maildir_deduplicate/__init__.py
maildir_deduplicate/cli.py
maildir_deduplicate/deduplicate.py
maildir_deduplicate/mail.py
maildir_deduplicate/tests/__init__.py
maildir_deduplicate/tests/case.py
maildir_deduplicate/tests/test_cli.py
maildir_deduplicate/tests/test_deduplicate.py
maildir_deduplicate-2.2.0.dist-info/LICENSE
maildir_deduplicate-2.2.0.dist-info/METADATA
maildir_deduplicate-2.2.0.dist-info/WHEEL
maildir_deduplicate-2.2.0.dist-info/entry_points.txt
maildir_deduplicate-2.2.0.dist-info/top_level.txt
maildir_deduplicate-2.2.0.dist-info/RECORD
