Metadata-Version: 2.1
Name: maildir-deduplicate
Version: 2.2.0
Summary: Deduplicate mails from a set of maildir folders.
Home-page: https://github.com/kdeldycke/maildir-deduplicate
Author: Kevin Deldycke
Author-email: kevin@deldycke.com
License: GPLv2+
Keywords: CLI,mail,email,maildir,deduplicate
Platform: UNKNOWN
Classifier: Development Status :: 5 - Production/Stable
Classifier: Environment :: Console
Classifier: Intended Audience :: Developers
Classifier: Intended Audience :: Information Technology
Classifier: License :: OSI Approved :: GNU General Public License v2 or later (GPLv2+)
Classifier: Operating System :: OS Independent
Classifier: Programming Language :: Python
Classifier: Programming Language :: Python :: 2
Classifier: Programming Language :: Python :: 2.7
Classifier: Programming Language :: Python :: 3
Classifier: Programming Language :: Python :: 3.4
Classifier: Programming Language :: Python :: 3.5
Classifier: Programming Language :: Python :: 3.6
Classifier: Programming Language :: Python :: Implementation :: CPython
Classifier: Programming Language :: Python :: Implementation :: PyPy
Classifier: Topic :: Communications :: Email
Classifier: Topic :: Utilities
Requires-Python: >= 2.7, != 3.0.*, != 3.1.*, != 3.2.*, != 3.3.*
Requires-Dist: boltons (>=16.3.0)
Requires-Dist: click (>=5.0)
Requires-Dist: click-log (>=0.2.0)
Requires-Dist: progressbar2
Requires-Dist: tabulate
Provides-Extra: develop
Requires-Dist: bumpversion ; extra == 'develop'
Requires-Dist: isort ; extra == 'develop'
Requires-Dist: readme-renderer (>=16.0) ; extra == 'develop'
Requires-Dist: setuptools (>=24.2.1wheel) ; extra == 'develop'
Provides-Extra: docs
Requires-Dist: sphinx (>=1.4) ; extra == 'docs'
Requires-Dist: sphinx-rtd-theme ; extra == 'docs'
Provides-Extra: tests
Requires-Dist: arrow ; extra == 'tests'
Requires-Dist: pycodestyle (>=2.1.0) ; extra == 'tests'
Requires-Dist: pylint ; extra == 'tests'
Requires-Dist: pytest ; extra == 'tests'
Requires-Dist: pytest-cov ; extra == 'tests'
